polarstypes/__init__.py
polarstypes/compress.py
polarstypes/custom_pivot.py
polarstypes/integers.py
polarstypes/relaxed_concat.py
polarstypes/strings.py
polarstypes-0.2.3.dist-info/LICENSE
polarstypes-0.2.3.dist-info/METADATA
polarstypes-0.2.3.dist-info/WHEEL
polarstypes-0.2.3.dist-info/entry_points.txt
polarstypes-0.2.3.dist-info/RECORD
