Metadata-Version: 2.1
Name: polarstypes
Version: 0.2.3
Summary: This library is for utility functions around the polars dataframe library, particularly compressing integer datatypes and also string to categorical.
License: MIT
Author: Isaac Moore
Author-email: isaacmooreuky@gmail.com
Requires-Python: >=3.10,<3.13
Classifier: License :: OSI Approved :: MIT License
Classifier: Programming Language :: Python :: 3
Classifier: Programming Language :: Python :: 3.10
Classifier: Programming Language :: Python :: 3.11
Requires-Dist: polars (>=0.18.13,<0.19.0)
